<annotation>
	<folder>JPEGImages</folder>
	<filename>114.jpg</filename>
	<path>C:\Users\Gabriel\mmdetection_object_detection_demo\data\VOC2007\JPEGImages\114.jpg</path>
	<source>
		<database>Unknown</database>
	</source>
	<size>
		<width>800</width>
		<height>600</height>
		<depth>3</depth>
	</size>
	<segmented>0</segmented>
	<object>
		<name>angus</name>
		<pose>Unspecified</pose>
		<truncated>0</truncated>
		<difficult>0</difficult>
		<bndbox>
			<xmin>294</xmin>
			<ymin>130</ymin>
			<xmax>402</xmax>
			<ymax>261</ymax>
		</bndbox>
	</object>
	<object>
		<name>angus</name>
		<pose>Unspecified</pose>
		<truncated>0</truncated>
		<difficult>0</difficult>
		<bndbox>
			<xmin>566</xmin>
			<ymin>144</ymin>
			<xmax>691</xmax>
			<ymax>273</ymax>
		</bndbox>
	</object>
	<object>
		<name>angus</name>
		<pose>Unspecified</pose>
		<truncated>0</truncated>
		<difficult>0</difficult>
		<bndbox>
			<xmin>397</xmin>
			<ymin>106</ymin>
			<xmax>507</xmax>
			<ymax>239</ymax>
		</bndbox>
	</object>
	<object>
		<name>angus</name>
		<pose>Unspecified</pose>
		<truncated>0</truncated>
		<difficult>0</difficult>
		<bndbox>
			<xmin>166</xmin>
			<ymin>96</ymin>
			<xmax>281</xmax>
			<ymax>224</ymax>
		</bndbox>
	</object>
	<object>
		<name>angus</name>
		<pose>Unspecified</pose>
		<truncated>0</truncated>
		<difficult>0</difficult>
		<bndbox>
			<xmin>95</xmin>
			<ymin>84</ymin>
			<xmax>188</xmax>
			<ymax>182</ymax>
		</bndbox>
	</object>
	<object>
		<name>angus</name>
		<pose>Unspecified</pose>
		<truncated>0</truncated>
		<difficult>0</difficult>
		<bndbox>
			<xmin>292</xmin>
			<ymin>79</ymin>
			<xmax>400</xmax>
			<ymax>131</ymax>
		</bndbox>
	</object>
	<object>
		<name>angus</name>
		<pose>Unspecified</pose>
		<truncated>0</truncated>
		<difficult>0</difficult>
		<bndbox>
			<xmin>510</xmin>
			<ymin>79</ymin>
			<xmax>619</xmax>
			<ymax>200</ymax>
		</bndbox>
	</object>
</annotation>
