<annotation>
	<folder>JPEGImages</folder>
	<filename>26.jpg</filename>
	<path>C:\Users\Gabriel\mmdetection_object_detection_demo\data\VOC2007\JPEGImages\26.jpg</path>
	<source>
		<database>Unknown</database>
	</source>
	<size>
		<width>800</width>
		<height>600</height>
		<depth>3</depth>
	</size>
	<segmented>0</segmented>
	<object>
		<name>angus</name>
		<pose>Unspecified</pose>
		<truncated>0</truncated>
		<difficult>0</difficult>
		<bndbox>
			<xmin>494</xmin>
			<ymin>202</ymin>
			<xmax>628</xmax>
			<ymax>317</ymax>
		</bndbox>
	</object>
	<object>
		<name>angus</name>
		<pose>Unspecified</pose>
		<truncated>0</truncated>
		<difficult>0</difficult>
		<bndbox>
			<xmin>346</xmin>
			<ymin>206</ymin>
			<xmax>490</xmax>
			<ymax>312</ymax>
		</bndbox>
	</object>
	<object>
		<name>angus</name>
		<pose>Unspecified</pose>
		<truncated>0</truncated>
		<difficult>0</difficult>
		<bndbox>
			<xmin>124</xmin>
			<ymin>45</ymin>
			<xmax>320</xmax>
			<ymax>197</ymax>
		</bndbox>
	</object>
</annotation>
